snakemake_executor_plugin_cluster_sync/__init__.py
snakemake_executor_plugin_cluster_sync-0.1.5.dist-info/LICENSE
snakemake_executor_plugin_cluster_sync-0.1.5.dist-info/METADATA
snakemake_executor_plugin_cluster_sync-0.1.5.dist-info/WHEEL
snakemake_executor_plugin_cluster_sync-0.1.5.dist-info/RECORD
